{
  "components": [
    {
      "tag": "my-app",
      "dependencies": [],
      "componentClass": "MyApp",
      "componentPath": "components/my-app/my-app.js",
      "styles": {
        "$": {
          "stylePaths": [
            "components/my-app/my-app.scss"
          ]
        }
      },
      "props": [
        {
          "name": "first",
          "type": "String"
        },
        {
          "name": "last",
          "type": "String"
        }
      ],
      "shadow": true
    }
  ],
  "collections": [],
  "compiler": {
    "name": "@stencil/core",
    "version": "0.6.8",
    "typescriptVersion": "2.7.2"
  }
}